gdrive_pydantic_wrapper/__init__.py
gdrive_pydantic_wrapper/_legacy/__init__.py
gdrive_pydantic_wrapper/_legacy/invoicing_tools/__init__.py
gdrive_pydantic_wrapper/_legacy/invoicing_tools/gdrive/__init__.py
gdrive_pydantic_wrapper/_legacy/invoicing_tools/gdrive/builders.py
gdrive_pydantic_wrapper/_legacy/invoicing_tools/gdrive/cli_commands.py
gdrive_pydantic_wrapper/_legacy/invoicing_tools/gdrive/db.py
gdrive_pydantic_wrapper/_legacy/invoicing_tools/gdrive/enums.py
gdrive_pydantic_wrapper/_legacy/invoicing_tools/gdrive/gdrive.py
gdrive_pydantic_wrapper/_legacy/invoicing_tools/gdrive/models.py
gdrive_pydantic_wrapper/_legacy/invoicing_tools/gdrive/utils.py
gdrive_pydantic_wrapper/cli.py
gdrive_pydantic_wrapper/clients.py
gdrive_pydantic_wrapper/exceptions.py
gdrive_pydantic_wrapper/google_drive/__init__.py
gdrive_pydantic_wrapper/google_drive/gdrive.py
gdrive_pydantic_wrapper/google_drive/gdrive_schemas.py
gdrive_pydantic_wrapper/py_google_drive.py
gdrive_pydantic_wrapper/schemas.py
gdrive_pydantic_wrapper-0.3.0.dist-info/LICENSE
gdrive_pydantic_wrapper-0.3.0.dist-info/METADATA
gdrive_pydantic_wrapper-0.3.0.dist-info/WHEEL
gdrive_pydantic_wrapper-0.3.0.dist-info/entry_points.txt
gdrive_pydantic_wrapper-0.3.0.dist-info/RECORD
